[
  { "symptomType": "Joint pain", 
    "rating": 
    { 
      "painLevel": "5", 
      "mood": "Bad"
    } 
  },
  { "symptomType": "Bruising", 
    "rating": 
    { 
      "painLevel": "9", 
      "mood": "Fine"
    } 
  },
  { "symptomType": "Constipation", 
    "rating": 
    { 
      "painLevel": "3", 
      "mood": "Fine"
    } 
  },
  { "symptomType": "Fever", 
    "rating": 
    { 
      "painLevel": "7", 
      "mood": "Bad"
    } 
  },
  { "symptomType": "Toothache", 
    "rating": 
    { 
      "painLevel": "1", 
      "mood": "Good"
    } 
  },
  { "symptomType": "Loss of appetite", 
    "rating": 
    { 
      "painLevel": "6", 
      "mood": "Fine"
    } 
  },
  { "symptomType": "Bloating", 
    "rating": 
    { 
      "painLevel": "1", 
      "mood": "Good"
    } 
  }
]